Metadata-Version: 2.1
Name: my-multiply
Version: 0.0.1
Summary: Multiplication of three numbers
Home-page: UNKNOWN
Author: pradeep
Author-email: mpradeepcseb@yahoo.com
License: MIT
Keywords: calculator
Platform: UNKNOWN
Classifier: Development Status :: 5 - Production/Stable
Classifier: Intended Audience :: Education
Classifier: Operating System :: Microsoft :: Windows :: Windows 10
Classifier: License :: OSI Approved :: MIT License
Classifier: Programming Language :: Python :: 3
License-File: LICENCE.txt
